<manifest alg="2" build="2018.1.0.386" opt="false" iceEnabled="true" iceMarkupVersion="2" iceEnabledOptions="link,responsive,cachebuster,textStyling" exportTarget="other" domain="personal.com" resolutions="1x" timestamp="1573538097533">
  <folder name="images">
    <file name="1048.jpg" crc="332197912" ref="index">
      <caption webpage="index" alt=""/>
    </file>
    <file name="asset 2.png" crc="4050967932" ref="index">
      <caption webpage="index" alt=""/>
    </file>
    <file name="asset 4.png" crc="49564336" ref="index">
      <caption webpage="index" alt=""/>
    </file>
  </folder>
  <folder name="css">
    <file name="site_global.css" crc="444006867"/>
    <file name="index.css" crc="88001283" ref="index"/>
  </folder>
  <folder name="scripts">
    <file name="jquery-1.8.3.min.js" crc="209076791" ref="index"/>
    <file name="museutils.js" crc="340535759" ref="index"/>
    <file name="whatinput.js" crc="86476730" ref="index"/>
    <file name="museconfig.js" crc="4286661555" ref="index"/>
    <file name="jquery.watch.js" crc="51536988" ref="index"/>
    <file name="require.js" crc="7928878" ref="index"/>
    <file name="jquery.musepolyfill.bgsize.js" crc="4260645839" ref="index"/>
  </folder>
  <file name="index.html" crc="4069514017" seo="true" mt="1573538086497" redirect="true"/>
</manifest>